gisgroup_statbank-0.0.2.dist-info/DESCRIPTION.rst
gisgroup_statbank-0.0.2.dist-info/METADATA
gisgroup_statbank-0.0.2.dist-info/RECORD
gisgroup_statbank-0.0.2.dist-info/WHEEL
gisgroup_statbank-0.0.2.dist-info/metadata.json
gisgroup_statbank-0.0.2.dist-info/top_level.txt
statbank/__init__.py
statbank/config.py
statbank/error.py
statbank/request.py
statbank/resources.py
statbank/time.py
statbank/url.py
