Metadata-Version: 2.0
Name: gisgroup-statbank
Version: 0.0.2
Summary: Statbank API client library
Home-page: http://github.com/gisgroup/statbank-python
Author: Gis Group ApS
Author-email: valentin@gisgroup.dk, zacharias@gisgroup.dk
License: MIT
Platform: UNKNOWN
Requires-Dist: python-dateutil
